resize_images/__init__.py
resize_images/plugin.py
mkdocs_resize_images-1.0.1.dist-info/LICENSE
mkdocs_resize_images-1.0.1.dist-info/METADATA
mkdocs_resize_images-1.0.1.dist-info/WHEEL
mkdocs_resize_images-1.0.1.dist-info/entry_points.txt
mkdocs_resize_images-1.0.1.dist-info/top_level.txt
mkdocs_resize_images-1.0.1.dist-info/RECORD
