Metadata-Version: 2.1
Name: mkdocs-resize-images
Version: 1.0.1
Summary: MkDocs plugin to resize images according to the configuration.
Home-page: https://github.com/JakubAndrysek/mkdocs-resize-images
Author: Jakub Andrýsek
Author-email: email@kubaandrysek.cz
License: MIT
Keywords: mkdocs plugin,resize images,mkdocs,plugin,images,resize
Classifier: License :: OSI Approved :: MIT License
Classifier: Programming Language :: Python :: 3.7
Classifier: Programming Language :: Python :: 3.8
Classifier: Programming Language :: Python :: 3.9
Classifier: Programming Language :: Python :: 3.10
Classifier: Programming Language :: Python :: 3.11
Classifier: Operating System :: OS Independent
Requires-Python: >=3.7
License-File: LICENSE
Requires-Dist: mkdocs
Requires-Dist: pillow
Provides-Extra: dev
Requires-Dist: mkdocs-material ; extra == 'dev'
Requires-Dist: mkdocs-open-in-new-tab ; extra == 'dev'
Requires-Dist: mkdocs-glightbox ; extra == 'dev'
Requires-Dist: mkdocs-git-revision-date-localized-plugin ; extra == 'dev'
Requires-Dist: cairosvg ; extra == 'dev'
Requires-Dist: pillow ; extra == 'dev'
